README.md
setup.py
recls/__init__.py
recls.egg-info/PKG-INFO
recls.egg-info/SOURCES.txt
recls.egg-info/dependency_links.txt
recls.egg-info/top_level.txt