Metadata-Version: 1.0
Name: recls
Version: 0.0.0.0
Summary: recls, for Python
Home-page: https://github.com/synesissoftware/recls.Python
Author: Matt Wilson
Author-email: matthew@synesis.com.au
License: BSD-3-Clause
Platform: UNKNOWN
